scalcbr/__init__.py
scalcbr/calc.py
scalcbr-0.0.1.dist-info/METADATA
scalcbr-0.0.1.dist-info/WHEEL
scalcbr-0.0.1.dist-info/top_level.txt
scalcbr-0.0.1.dist-info/RECORD
