Metadata-Version: 2.1
Name: scalcbr
Version: 0.0.1
Summary: Simple Calc
Home-page: https://github.com/DanielVictorSR/simple_calculator_package.git
Author: Daniel Victor
License: UNKNOWN
Platform: UNKNOWN
Requires-Python: >=3.7
Requires-Dist: numpy
